libtidy/__about__.py
libtidy/__config__.py
libtidy/__init__.py
libtidy/_config.py
libtidy/_dll.py
libtidy/_tidy.py
libtidy/_tidybuffio.py
libtidy/_tidyenum.py
libtidy/_tidyplatform.py
libtidy/libtidy.cfg
libtidy/tidy.py
libtidy/_platform/__init__.py
libtidy/_platform/_platform.py
libtidy/_platform/_linux/__init__.py
libtidy/_platform/_linux/aarch64/.keep
libtidy/_platform/_linux/x64/libtidy.so
libtidy/_platform/_linux/x86/.keep
libtidy/_platform/_macos/__init__.py
libtidy/_platform/_macos/x64/10.7/.keep
libtidy/_platform/_macos/x64/11.6/.keep
libtidy/_platform/_macos/x86/.keep
libtidy/_platform/_windows/__init__.py
libtidy/_platform/_windows/_win32.py
libtidy/_platform/_windows/x64/tidy.dll
libtidy/_platform/_windows/x86/.keep
libtidy/console/tidy.py
libtidy-5.9.14b3.dist-info/licenses/LICENSE
libtidy-5.9.14b3.dist-info/METADATA
libtidy-5.9.14b3.dist-info/WHEEL
libtidy-5.9.14b3.dist-info/entry_points.txt
libtidy-5.9.14b3.dist-info/top_level.txt
libtidy-5.9.14b3.dist-info/RECORD
